tcod_ansi_terminal/__init__.py
tcod_ansi_terminal/_abstract_context.py
tcod_ansi_terminal/_ansi.py
tcod_ansi_terminal/_console_utils.py
tcod_ansi_terminal/_internal_context.py
tcod_ansi_terminal/_internal_event.py
tcod_ansi_terminal/_logging.py
tcod_ansi_terminal/_presenters.py
tcod_ansi_terminal/context.py
tcod_ansi_terminal/event.py
tcod_ansi_terminal/py.typed
tcod_ansi_terminal/_platform/__init__.py
tcod_ansi_terminal/_platform/_abstract_platform.py
tcod_ansi_terminal/_platform/_unix.py
tcod_ansi_terminal/_platform/_windows.py
tcod_ansi_terminal-0.1.0.dist-info/LICENCE
tcod_ansi_terminal-0.1.0.dist-info/METADATA
tcod_ansi_terminal-0.1.0.dist-info/WHEEL
tcod_ansi_terminal-0.1.0.dist-info/top_level.txt
tcod_ansi_terminal-0.1.0.dist-info/RECORD
