Metadata-Version: 2.1
Name: tcod-ansi-terminal
Version: 0.1.0
Summary: ANSI terminal support for Python TCOD.
Author-email: Max Whitney <mwhitney@alumni.sfu.ca>
License: BSD-3-Clause
Keywords: roguelike,libtcod,terminal,ansi
Classifier: Development Status :: 4 - Beta
Classifier: License :: OSI Approved :: BSD License
Classifier: Programming Language :: Python :: 3
Classifier: Programming Language :: Python :: 3.8
Classifier: Programming Language :: Python :: 3.9
Classifier: Programming Language :: Python :: 3.10
Classifier: Programming Language :: Python :: 3.11
Classifier: Intended Audience :: Developers
Classifier: Environment :: Console
Classifier: Operating System :: Unix
Classifier: Operating System :: MacOS :: MacOS X
Classifier: Topic :: Terminals
Classifier: Topic :: Games/Entertainment
Classifier: Topic :: Multimedia :: Graphics
Classifier: Topic :: Software Development :: Libraries :: Python Modules
Classifier: Typing :: Typed
Requires-Python: >3.8
License-File: LICENCE
Requires-Dist: numpy
Requires-Dist: tcod ~=16.2
Requires-Dist: typing-extensions ~=4.7 ; python_version < "3.8"
